topcat-0.2.3.dist-info/METADATA
topcat-0.2.3.dist-info/WHEEL
topcat/__init__.py
topcat/__main__.py
topcat-0.2.3.data/scripts/topcat.exe
topcat-0.2.3.dist-info/RECORD
