Metadata-Version: 2.4
Name: topcat
Version: 0.2.3
Classifier: Development Status :: 3 - Alpha
Classifier: Environment :: Console
Classifier: Intended Audience :: Developers
Classifier: License :: OSI Approved :: MIT License
Classifier: Operating System :: OS Independent
Classifier: Programming Language :: Python
Classifier: Programming Language :: Python :: 3.7
Classifier: Programming Language :: Python :: 3.8
Classifier: Programming Language :: Python :: 3.9
Classifier: Programming Language :: Python :: 3.10
Classifier: Programming Language :: Python :: 3.11
Classifier: Programming Language :: Python :: 3.12
Classifier: Programming Language :: Python :: 3 :: Only
Classifier: Programming Language :: Rust
Classifier: Topic :: Software Development :: Libraries :: Python Modules
Summary: A tool for concatenating files in topological order
Keywords: file,dependency,topological,graph,concatenation
Author: josha@jci.dev
Author-email: Josha Inglis <joshainglis@gmail.com>
License: MIT
Requires-Python: >=3.7
Project-URL: Repository, https://github.com/joshainglis/topcat
